{
  "meta": {
    "version": "2.0.0",
    "timestamp": "2026-03-18T09:02:47.766076+00:00",
    "config_used": {
      "opponent_penalty_lambda": 0.2,
      "top_n": 5
    },
    "team_name": "Al-Hilal",
    "opponent_name": "Al-Najma",
    "total_scenarios": 1
  },
  "results": [
    {
      "scenario_id": "S3_min58",
      "scenario_label": "Espulsione L\u00c3\u00a1zaro per condotta violenta (58'). Superiorit\u00c3\u00a0 numerica 11v10, risultato 1-1. Opportunit\u00c3\u00a0 tattica.",
      "match_conditions": {
        "time_remaining": 32.0,
        "score_diff": 0,
        "fatigue_level": 0.58,
        "morale": 0.7
      },
      "best_strategy": {
        "strategy": "Overlapping Flanks",
        "adjusted_distance": 0.2214,
        "raw_distance": 0.3618,
        "category": "offensive"
      },
      "baseline_strategy": {
        "strategy": "Build-up Play",
        "adjusted_distance": 0.3562,
        "raw_distance": 0.3562,
        "category": "offensive"
      },
      "ranking": [
        {
          "strategy": "Overlapping Flanks",
          "adjusted_distance": 0.2214,
          "raw_distance": 0.3618,
          "category": "offensive"
        },
        {
          "strategy": "Build-up Play",
          "adjusted_distance": 0.2309,
          "raw_distance": 0.3562,
          "category": "offensive"
        },
        {
          "strategy": "Systematic Crossing",
          "adjusted_distance": 0.2621,
          "raw_distance": 0.391,
          "category": "offensive"
        },
        {
          "strategy": "Extended Possession Play",
          "adjusted_distance": 0.2915,
          "raw_distance": 0.4158,
          "category": "possession"
        },
        {
          "strategy": "Quick Rotations in Attack",
          "adjusted_distance": 0.2931,
          "raw_distance": 0.4323,
          "category": "offensive"
        }
      ]
    }
  ]
}